crypto/aes.py
crypto/dh.py
crypto/ecc.py
crypto/ecdsa.py
crypto/elgamal.py
crypto/hmac.py
crypto/hybrid.py
crypto/rsa.py
crypto/sha256.py
crypto/signature.py
privhat-0.1.0.dist-info/METADATA
privhat-0.1.0.dist-info/WHEEL
privhat-0.1.0.dist-info/entry_points.txt
privhat-0.1.0.dist-info/top_level.txt
privhat-0.1.0.dist-info/RECORD
