Metadata-Version: 2.4
Name: privhat
Version: 0.1.0
Summary: Cryptography CLI Tool
Author: ayiman29
License-Expression: MIT
Keywords: crypto,CLI
Classifier: Programming Language :: Python :: 3
Classifier: Operating System :: OS Independent
Requires-Python: >=3.7
Requires-Dist: colorama
